tidy3dclient/__init__.py
tidy3dclient/constants.py
tidy3dclient/dispersion.py
tidy3dclient/grid.py
tidy3dclient/json_ops.py
tidy3dclient/material.py
tidy3dclient/material_library.py
tidy3dclient/simulation.py
tidy3dclient/structure.py
tidy3dclient/utils.py
tidy3dclient/mode/Mode.py
tidy3dclient/mode/ModePlane.py
tidy3dclient/mode/__init__.py
tidy3dclient/mode/derivatives.py
tidy3dclient/mode/dot_product.py
tidy3dclient/mode/solver.py
tidy3dclient/monitor/Monitor.py
tidy3dclient/monitor/MonitorData.py
tidy3dclient/monitor/__init__.py
tidy3dclient/monitor/_simulation.py
tidy3dclient/source/Source.py
tidy3dclient/source/SourceData.py
tidy3dclient/source/SourceTime.py
tidy3dclient/source/__init__.py
tidy3dclient/source/_simulation.py
tidy3dclient/utils/__init__.py
tidy3dclient/utils/check.py
tidy3dclient/utils/em.py
tidy3dclient/utils/geom.py
tidy3dclient/utils/log.py
tidy3dclient/utils/misc.py
tidy3dclient/viz/__init__.py
tidy3dclient/viz/field.py
tidy3dclient/viz/mode.py
tidy3dclient/viz/source.py
tidy3dclient/viz/structure.py
tidy3dclient/web/__init__.py
tidy3dclient/web/authentication.py
tidy3dclient/web/config.py
tidy3dclient/web/httputils.py
tidy3dclient/web/s3utils.py
tidy3dclient/web/webapi.py
tidy3dclient-0.2.1.3.dist-info/METADATA
tidy3dclient-0.2.1.3.dist-info/WHEEL
tidy3dclient-0.2.1.3.dist-info/dependency_links.txt
tidy3dclient-0.2.1.3.dist-info/top_level.txt
tidy3dclient-0.2.1.3.dist-info/RECORD
