Metadata-Version: 2.1
Name: tidy3dclient
Version: 0.2.1.3
Summary: A Python API for Tidy3D FDTD Solver
Home-page: UNKNOWN
Author: FlexCompute, Inc.
Author-email: lei@flexcompute.com
License: UNKNOWN
Platform: UNKNOWN
Classifier: Programming Language :: Python :: 3
Classifier: Operating System :: OS Independent
Requires-Python: >=3.6
Requires-Dist: aws-requests-auth
Requires-Dist: bcrypt
Requires-Dist: matplotlib (>=3.0.3)
Requires-Dist: numpy (>=1.19.0)
Requires-Dist: scipy (>=1.5.1)
Requires-Dist: gdspy (>=1.6.1)
Requires-Dist: h5py (>=2.10.0)
Requires-Dist: boto3 (~=1.15.11)
Requires-Dist: requests (~=2.22.0)
Requires-Dist: setuptools (>=53.0.0)
